cli_tool/__init__.py
cli_tool/ai_analyzer.py
cli_tool/analyzer.py
cli_tool/main.py
cli_tool/report_generator.py
git_analyzer/__init__.py
git_analyzer/core/__init__.py
git_analyzer/core/analyzer.py
git_analyzer/core/challenge_detector.py
git_analyzer/core/clustering.py
git_analyzer/core/contributor_analyzer.py
git_analyzer/core/impact_analyzer.py
git_analyzer/core/milestone_detector.py
git_analyzer/llm/__init__.py
git_analyzer/llm/llm_analyzer.py
git_analyzer/llm/report_generator.py
git_repo_intelligence/__init__.py
git_repo_intelligence/version.py
git_repo_intelligence-0.1.0.dist-info/LICENSE
git_repo_intelligence-0.1.0.dist-info/METADATA
git_repo_intelligence-0.1.0.dist-info/WHEEL
git_repo_intelligence-0.1.0.dist-info/entry_points.txt
git_repo_intelligence-0.1.0.dist-info/top_level.txt
git_repo_intelligence-0.1.0.dist-info/RECORD
