Metadata-Version: 2.1
Name: git-repo-intelligence
Version: 0.1.0
Summary: Git Repository Intelligence Platform - AI-driven repository insights
Home-page: https://github.com/mehulprajapati2802/git-repo-intelligence
Author: Mehul Prajapati
Author-email: mehulprajapati2802@gmail.com
License: UNKNOWN
Keywords: git,analytics,repository,insights,ai,llm,developer,intelligence
Platform: UNKNOWN
Classifier: Programming Language :: Python :: 3
Classifier: Programming Language :: Python :: 3.8
Classifier: Programming Language :: Python :: 3.9
Classifier: Programming Language :: Python :: 3.10
Classifier: License :: OSI Approved :: MIT License
Classifier: Operating System :: OS Independent
Classifier: Topic :: Software Development :: Version Control :: Git
Classifier: Topic :: Software Development :: Documentation
Requires-Python: >=3.8
License-File: LICENSE
Requires-Dist: gitpython>=3.1.30
Requires-Dist: numpy>=1.23.0
Requires-Dist: scikit-learn>=1.2.0
Requires-Dist: nltk>=3.8.0
Requires-Dist: requests>=2.28.0
Requires-Dist: openai>=0.27.0
Provides-Extra: full
Requires-Dist: pdfkit>=1.0.0; extra == "full"
Requires-Dist: markdown>=3.4.0; extra == "full"
Provides-Extra: markdown
Requires-Dist: markdown>=3.4.0; extra == "markdown"
Provides-Extra: pdf
Requires-Dist: pdfkit>=1.0.0; extra == "pdf"
